setup.py
rollcat/__init__.py
rollcat/cat.py
rollcat.egg-info/PKG-INFO
rollcat.egg-info/SOURCES.txt
rollcat.egg-info/dependency_links.txt
rollcat.egg-info/entry_points.txt
rollcat.egg-info/not-zip-safe
rollcat.egg-info/requires.txt
rollcat.egg-info/top_level.txt