Metadata-Version: 1.1
Name: rollcat
Version: 0.2.1
Summary: Rainbows and unicorns!
Home-page: https://github.com/pyrocat101/rollcat/
Author: Linjie Ding
Author-email: i@pyroc.at
License: MIT
Keywords: cat,rainbow
Platform: UNKNOWN
Classifier: Development Status :: 4 - Beta
Classifier: Topic :: Utilities
Classifier: License :: OSI Approved :: MIT License
Classifier: Environment :: Console
